HISTORY.rst
LICENSE
MANIFEST.in
README.rst
setup.cfg
setup.py
docs/Makefile
docs/api.rst
docs/conf.py
docs/index.rst
docs/make.bat
nass/__init__.py
nass/api.py
nass/exceptions.py
nass/query.py
nass.egg-info/PKG-INFO
nass.egg-info/SOURCES.txt
nass.egg-info/dependency_links.txt
nass.egg-info/requires.txt
nass.egg-info/top_level.txt
tests/test_api.py
tests/test_exceptions.py
tests/test_query.py
tests/util.py